disk_usage_exporter/__init__.py
disk_usage_exporter/const.py
disk_usage_exporter/disk_usage_exporter.py
disk_usage_exporter/release.py
disk_usage_exporter/utils.py
disk_usage_exporter-0.1.0.dist-info/licenses/LICENSE
disk_usage_exporter-0.1.0.dist-info/METADATA
disk_usage_exporter-0.1.0.dist-info/WHEEL
disk_usage_exporter-0.1.0.dist-info/entry_points.txt
disk_usage_exporter-0.1.0.dist-info/top_level.txt
disk_usage_exporter-0.1.0.dist-info/RECORD
