Metadata-Version: 2.4
Name: disk_usage_exporter
Version: 0.1.0
Summary: Exporter for disk usage metrics
Author-email: Murad Murtuzaliev <muradmurtuzaliev404@gmail.com>
Classifier: Programming Language :: Python :: 3
Classifier: Programming Language :: Python :: 3.8
Classifier: Programming Language :: Python :: 3.9
Classifier: Programming Language :: Python :: 3.10
Classifier: Programming Language :: Python :: 3.11
Classifier: Programming Language :: Python :: 3.12
Classifier: Programming Language :: Python :: 3.13
Classifier: Operating System :: POSIX :: Linux
Classifier: License :: OSI Approved :: GNU General Public License v3 (GPLv3)
Classifier: Topic :: System :: Monitoring
Requires-Python: >=3.8
License-File: LICENSE
Requires-Dist: prometheus_client==0.21.1
Requires-Dist: setproctitle==1.3.5
Requires-Dist: sh==2.2.1
Provides-Extra: test
Requires-Dist: requests==2.32.3; extra == "test"
Requires-Dist: pytest==8.3.4; extra == "test"
Dynamic: license-file
